cloudfn/core/__init__.py
cloudfn/core/cli.py
cloudfn/core/common.py
cloudfn/core/data.py
cloudfn/core/io.py
cloudfn/core/util.py
cloudfn_core-0.2.12.dist-info/METADATA
cloudfn_core-0.2.12.dist-info/WHEEL
cloudfn_core-0.2.12.dist-info/entry_points.txt
cloudfn_core-0.2.12.dist-info/top_level.txt
cloudfn_core-0.2.12.dist-info/RECORD
