Metadata-Version: 2.1
Name: cloudfn-core
Version: 0.2.12
Summary: cloudfn-core
Home-page: https://github.com/akrymskiy/cloudfn
Author: Aleksandr Krymskiy
Author-email: alex@krymskiy.net
License: MIT
Requires-Python: >=3.9
